version_query/__init__.py
version_query/__main__.py
version_query/_version.py
version_query/git_query.py
version_query/local_git_version.py
version_query/main.py
version_query/parser.py
version_query/patterns.py
version_query/py.typed
version_query/py_query.py
version_query/query.py
version_query/version.py
version_query-1.7.0.dist-info/licenses/LICENSE
version_query-1.7.0.dist-info/licenses/NOTICE
version_query-1.7.0.dist-info/METADATA
version_query-1.7.0.dist-info/WHEEL
version_query-1.7.0.dist-info/top_level.txt
version_query-1.7.0.dist-info/RECORD
